src/__init__.py
src/main.py
outliersdemo-0.1.dist-info/LICENSE
outliersdemo-0.1.dist-info/WHEEL
outliersdemo-0.1.dist-info/METADATA
outliersdemo-0.1.dist-info/RECORD
